nonconvexoptimizationlib/__init__.py
nonconvexoptimizationlib/nonconvexfunctions.py
nonconvexoptimzationfunclib-0.0.1.dist-info/METADATA
nonconvexoptimzationfunclib-0.0.1.dist-info/WHEEL
nonconvexoptimzationfunclib-0.0.1.dist-info/top_level.txt
nonconvexoptimzationfunclib-0.0.1.dist-info/RECORD
