Metadata-Version: 2.1
Name: nonconvexoptimzationfunclib
Version: 0.0.1
Summary: A library of non-convex optimization functions containing continuous and non-conitnuous functions implemented in higher dimensions
Author: Dr.Thanos{CSU Fresno} and Satyam Mittal{CSU Fresno}
Author-email: satyam101905@gmail.com
Classifier: Development Status :: 4 - Beta
Classifier: Intended Audience :: Developers
Classifier: Topic :: Software Development :: Libraries
Classifier: Programming Language :: Python :: 3
Classifier: Operating System :: Unix
Classifier: Operating System :: MacOS :: MacOS X
Classifier: Operating System :: Microsoft :: Windows
Classifier: License :: OSI Approved :: MIT License
Requires-Dist: numpy
